aulas/change_bits/control.vhd
entity control is
    port(
        clock, reset, vai: in bit;
        loadA, loadB, selEntrada, pronto: out bit
    );
end entity;

architecture arch of control is
    type estados is (s0, s1, s2, s3, s4, s5);
    signal atual, prox: estados;
begin
    process(clock, reset)
    begin
        if reset = '1' then
            atual <= s0;
        elsif clock = '1' and clock'event then
            atual <= prox;
        end if;
    end process;

    prox <=
        s0 when atual = s0 and vai = '0' else
        s1 when atual = s0 and vai = '1' else
        s2 when atual = s1 else
        s3 when atual = s2 else
        s4 when atual = s3 else
        s5 when atual = s4 else
        s0;

    loadA <= '1' when atual = s1 or atual = s2 or atual = s4
    else '0';
    loadB <= '1' when atual = s1 or atual = s3
    else '0';
    selEntrada <= '1' when atual = s2 or atual = s3 or atual = s4
    else '0';

    pronto <= '1' when atual = s5 else '0';

end arch;

aulas/change_bits/register.vhd
library ieee;
use ieee.numeric_bit.rising_edge;

entity reg is
    port(
        clock, reset, load: in bit;
        carga: in bit_vector(3 downto 0);
        saida: out bit_vector(3 downto 0)
    );
end entity;

architecture arch of reg is
begin
process(clock, reset, load)
begin
    if reset = '1' then
        saida <= (others => '0');
    elsif rising_edge(clock) then -- marca flip flop
        if load = '1' then
            saida <= carga;
        end if;
    end if;
end process;
end arch;

aulas/change_bits/fd.vhd
entity fd is
  port (
    clock, reset: in bit;
    loadA, loadB, selEntrada: in bit;
    A, B: in bit_vector(3 downto 0)
  );
end entity;

architecture arch of fd is
  component reg is
    port (
      clock, reset, load: in bit;
      carga: in bit_vector(3 downto 0);
      saida: out bit_vector(3 downto 0)
    );
  end component;
  signal entradaA, entradaB, saidaA, saidaB, tmpXor: bit_vector(3 downto 0);
begin
  regA: reg port map(clock, reset, loadA, entradaA, saidaA);
  regB: reg port map(clock, reset, loadB, entradaB, saidaB);

  entradaA <= A when selEntrada = '0' else tmpXor;
  entradaB <= B when selEntrada = '0' else tmpXor;

  genXors: for i in 3 downto 0 generate
    tmpXor(i) <= saidaA(i) xor saidaB(i);
  end generate;

end architecture;

aulas/change_bits/toplevel.vhd
entity toplevel is
    port(
        clock, reset, vai: in bit;
        cargaA, cargaB: in bit_vector(3 downto 0); 
        pronto: out bit
    );
end entity;

architecture arch of toplevel is

    component fd is
        port (
          clock, reset: in bit;
          loadA, loadB, selEntrada: in bit;
          A, B: in bit_vector(3 downto 0)
        );
    end component;

    component control is
        port(
            clock, reset, vai: in bit;
            loadA, loadB, selEntrada, pronto: out bit
        );
    end component;

    signal lA, lB, sE: bit;

begin

    fluxo: fd port map(clock, reset, lA, lB, sE, cargaA, cargaB);
    controle: control port map(clock, reset, vai, lA, lB, sE, pronto);

end arch;

aulas/change_bits/toplevel_tb.vhd
entity toplevel_tb is 
end entity;

architecture arch of toplevel_tb is

    component toplevel is
        port(
            clock, reset, vai: in bit;
            cargaA, cargaB: in bit_vector(3 downto 0); 
            pronto: out bit
        );
    end component;

    signal clk, rst, vai, pronto, simula: bit;
    signal A, B: bit_vector(3 downto 0);

begin

    dut: toplevel port map(clk, rst, vai, A, B, pronto);

    clk <= (simula and not clk) after 1 ns;

    tb: process
    begin
        simula <= '1';
        report "BOT";

        A <= "0111";
        B <= "0101";

        rst <= '1'; wait for 5 ns; rst <= '0';
        vai <= '1';
        wait for 2 ns;
        vai <= '0';
        wait for 20 ns;

        report "EOT";
        simula <= '0';
        wait;
    end process;

end architecture arch;

aulas/change_bits/wave.vcd
$date
  Fri Nov  6 14:58:02 2020
$end
$version
  GHDL v0
$end
$timescale
  1 fs
$end
$scope module standard $end
$upscope $end
$scope module numeric_bit $end
$upscope $end
$scope module toplevel_tb $end
$var reg 1 ! clk $end
$var reg 1 " rst $end
$var reg 1 # vai $end
$var reg 1 $ pronto $end
$var reg 1 % simula $end
$var reg 4 & a[3:0] $end
$var reg 4 ' b[3:0] $end
$scope module dut $end
$var reg 1 ( clock $end
$var reg 1 ) reset $end
$var reg 1 * vai $end
$var reg 4 + cargaa[3:0] $end
$var reg 4 , cargab[3:0] $end
$var reg 1 - pronto $end
$var reg 1 . la $end
$var reg 1 / lb $end
$var reg 1 0 se $end
$scope module fluxo $end
$var reg 1 1 clock $end
$var reg 1 2 reset $end
$var reg 1 3 loada $end
$var reg 1 4 loadb $end
$var reg 1 5 selentrada $end
$var reg 4 6 a[3:0] $end
$var reg 4 7 b[3:0] $end
$var reg 4 8 entradaa[3:0] $end
$var reg 4 9 entradab[3:0] $end
$var reg 4 : saidaa[3:0] $end
$var reg 4 ; saidab[3:0] $end
$var reg 4 < tmpxor[3:0] $end
$scope module rega $end
$var reg 1 = clock $end
$var reg 1 > reset $end
$var reg 1 ? load $end
$var reg 4 @ carga[3:0] $end
$var reg 4 A saida[3:0] $end
$upscope $end
$scope module regb $end
$var reg 1 B clock $end
$var reg 1 C reset $end
$var reg 1 D load $end
$var reg 4 E carga[3:0] $end
$var reg 4 F saida[3:0] $end
$upscope $end
$scope module genxors(0) $end
$upscope $end
$scope module genxors(1) $end
$upscope $end
$scope module genxors(2) $end
$upscope $end
$scope module genxors(3) $end
$upscope $end
$upscope $end
$scope module controle $end
$var reg 1 G clock $end
$var reg 1 H reset $end
$var reg 1 I vai $end
$var reg 1 J loada $end
$var reg 1 K loadb $end
$var reg 1 L selentrada $end
$var reg 1 M pronto $end
$comment atual is not handled $end
$comment prox is not handled $end
$upscope $end
$upscope $end
$upscope $end
$enddefinitions $end
#0
0!
1"
0#
0$
1%
b0111 &
b0101 '
0(
1)
0*
b0111 +
b0101 ,
0-
0.
0/
00
01
12
03
04
05
b0111 6
b0101 7
b0111 8
b0101 9
b0000 :
b0000 ;
b0000 <
0=
1>
0?
b0111 @
b0000 A
0B
1C
0D
b0101 E
b0000 F
0G
1H
0I
0J
0K
0L
0M
#1000000
1!
1(
11
1=
1B
1G
#2000000
0!
0(
01
0=
0B
0G
#3000000
1!
1(
11
1=
1B
1G
#4000000
0!
0(
01
0=
0B
0G
#5000000
1!
0"
1#
1(
0)
1*
11
02
1=
0>
1B
0C
1G
0H
1I
#6000000
0!
0(
01
0=
0B
0G
#7000000
1!
0#
1(
0*
1.
1/
11
13
14
1=
1?
1B
1D
1G
0I
1J
1K
#8000000
0!
0(
01
0=
0B
0G
#9000000
1!
1(
0/
10
11
04
15
b0010 8
b0010 9
b0111 :
b0101 ;
b0010 <
1=
b0010 @
b0111 A
1B
0D
b0010 E
b0101 F
1G
0K
1L
#10000000
0!
0(
01
0=
0B
0G
#11000000
1!
1(
0.
1/
11
03
14
b0111 8
b0111 9
b0010 :
b0111 <
1=
0?
b0111 @
b0010 A
1B
1D
b0111 E
1G
0J
1K
#12000000
0!
0(
01
0=
0B
0G
#13000000
1!
1(
1.
0/
11
13
04
b0101 8
b0101 9
b0111 ;
b0101 <
1=
1?
b0101 @
1B
0D
b0101 E
b0111 F
1G
1J
0K
#14000000
0!
0(
01
0=
0B
0G
#15000000
1!
1$
1(
1-
0.
00
11
03
05
b0111 8
b0101 :
b0010 <
1=
0?
b0111 @
b0101 A
1B
1G
0J
0L
1M
#16000000
0!
0(
01
0=
0B
0G
#17000000
1!
0$
1(
0-
11
1=
1B
1G
0M
#18000000
0!
0(
01
0=
0B
0G
#19000000
1!
1(
11
1=
1B
1G
#20000000
0!
0(
01
0=
0B
0G
#21000000
1!
1(
11
1=
1B
1G
#22000000
0!
0(
01
0=
0B
0G
#23000000
1!
1(
11
1=
1B
1G
#24000000
0!
0(
01
0=
0B
0G
#25000000
1!
1(
11
1=
1B
1G
#26000000
0!
0(
01
0=
0B
0G
#27000000
1!
0%
1(
11
1=
1B
1G
